func_adl_uproot/__init__.py
func_adl_uproot/dataset.py
func_adl_uproot/executor.py
func_adl_uproot/transformer.py
func_adl_uproot/translation.py
func_adl_uproot-2.2.0.dist-info/LICENSE
func_adl_uproot-2.2.0.dist-info/METADATA
func_adl_uproot-2.2.0.dist-info/WHEEL
func_adl_uproot-2.2.0.dist-info/top_level.txt
func_adl_uproot-2.2.0.dist-info/RECORD
