Metadata-Version: 2.1
Name: func_adl_uproot
Version: 2.2.0
Summary: Functional Analysis Description Language uproot backend for accessing flat ROOT ntuples
Home-page: https://github.com/iris-hep/func_adl_uproot
Author: Mason Proffitt
Author-email: masonlp@uw.edu
Requires-Python: >=3.8, <3.14
License-File: LICENSE
Requires-Dist: awkward >=2.0.9
Requires-Dist: dask-awkward >=2023.8.1
Requires-Dist: func-adl !=3.3.1,!=3.3.2,!=3.3.3,>=3.2.7
Requires-Dist: numpy
Requires-Dist: qastle >=0.18.0
Requires-Dist: uproot >=5
Requires-Dist: vector >=1.1.0
Provides-Extra: test
Requires-Dist: flake8 ; extra == 'test'
Requires-Dist: pytest ; extra == 'test'
Requires-Dist: pytest-cov ; extra == 'test'
